sj_sync/__init__.py
sj_sync/models.py
sj_sync/position_sync.py
sj_sync/types.py
sj_sync-0.1.7.dist-info/WHEEL
sj_sync-0.1.7.dist-info/entry_points.txt
sj_sync-0.1.7.dist-info/METADATA
sj_sync-0.1.7.dist-info/RECORD
