Metadata-Version: 2.3
Name: sj-sync
Version: 0.1.7
Summary: Real-time position synchronization for Shioaji
Keywords: shioaji,trading,position,real-time,taiwan,stock
Author: yvictor
Author-email: yvictor <yvictor3141@gmail.com>
License: MIT
Classifier: Development Status :: 4 - Beta
Classifier: Intended Audience :: Developers
Classifier: Intended Audience :: Financial and Insurance Industry
Classifier: License :: OSI Approved :: MIT License
Classifier: Programming Language :: Python :: 3
Classifier: Programming Language :: Python :: 3.10
Classifier: Programming Language :: Python :: 3.11
Classifier: Programming Language :: Python :: 3.12
Classifier: Programming Language :: Python :: 3.13
Classifier: Programming Language :: Python :: 3.14
Classifier: Topic :: Office/Business :: Financial :: Investment
Classifier: Topic :: Software Development :: Libraries :: Python Modules
Requires-Dist: shioaji>=1.2.0
Requires-Dist: pydantic>=2.0.0
Requires-Dist: loguru>=0.7.0
Requires-Python: >=3.10
Project-URL: Homepage, https://github.com/yvictor/sj_sync
Project-URL: Issues, https://github.com/yvictor/sj_sync/issues
Project-URL: Repository, https://github.com/yvictor/sj_sync
